exonware/__init__.py
exonware/xwdata/__init__.py
exonware/xwdata/base.py
exonware/xwdata/builder.py
exonware/xwdata/config.py
exonware/xwdata/contracts.py
exonware/xwdata/defs.py
exonware/xwdata/errors.py
exonware/xwdata/facade.py
exonware/xwdata/shortcuts.py
exonware/xwdata/version.py
exonware/xwdata/common/__init__.py
exonware/xwdata/common/benchmarking.py
exonware/xwdata/common/caching/__init__.py
exonware/xwdata/common/caching/base.py
exonware/xwdata/common/caching/cache_manager.py
exonware/xwdata/common/caching/contracts.py
exonware/xwdata/common/caching/strategies.py
exonware/xwdata/common/monitoring/__init__.py
exonware/xwdata/common/monitoring/metrics.py
exonware/xwdata/common/monitoring/performance.py
exonware/xwdata/common/patterns/__init__.py
exonware/xwdata/common/patterns/factory.py
exonware/xwdata/common/patterns/registry.py
exonware/xwdata/data/__init__.py
exonware/xwdata/data/base.py
exonware/xwdata/data/contracts.py
exonware/xwdata/data/engine.py
exonware/xwdata/data/factory.py
exonware/xwdata/data/lazy.py
exonware/xwdata/data/node.py
exonware/xwdata/data/metadata/__init__.py
exonware/xwdata/data/metadata/base.py
exonware/xwdata/data/metadata/contracts.py
exonware/xwdata/data/metadata/extractor.py
exonware/xwdata/data/metadata/processor.py
exonware/xwdata/data/metadata/universal.py
exonware/xwdata/data/references/__init__.py
exonware/xwdata/data/references/base.py
exonware/xwdata/data/references/contracts.py
exonware/xwdata/data/references/detector.py
exonware/xwdata/data/references/patterns.py
exonware/xwdata/data/references/resolver.py
exonware/xwdata/data/strategies/__init__.py
exonware/xwdata/data/strategies/base.py
exonware/xwdata/data/strategies/contracts.py
exonware/xwdata/data/strategies/csv.py
exonware/xwdata/data/strategies/json.py
exonware/xwdata/data/strategies/registry.py
exonware/xwdata/data/strategies/toml.py
exonware/xwdata/data/strategies/xml.py
exonware/xwdata/data/strategies/yaml.py
exonware/xwdata/operations/__init__.py
exonware_xwdata-0.1.0.1.dist-info/METADATA
exonware_xwdata-0.1.0.1.dist-info/WHEEL
exonware_xwdata-0.1.0.1.dist-info/licenses/LICENSE
exonware_xwdata-0.1.0.1.dist-info/RECORD
