Metadata-Version: 2.4
Name: exonware-xwdata
Version: 0.1.0.1
Summary: Advanced data manipulation with XWNode integration, async operations, and universal format conversion
Project-URL: Homepage, https://exonware.com
Project-URL: Repository, https://github.com/exonware/xdata
Project-URL: Documentation, https://github.com/exonware/xdata#readme
Author-email: "Eng. Muhammad AlShehri" <connect@exonware.com>
License: MIT
License-File: LICENSE
Keywords: analysis,data,exonware,manipulation,processing,transformation
Classifier: Development Status :: 3 - Alpha
Classifier: Intended Audience :: Developers
Classifier: License :: OSI Approved :: MIT License
Classifier: Operating System :: OS Independent
Classifier: Programming Language :: Python :: 3
Classifier: Programming Language :: Python :: 3.12
Classifier: Topic :: Software Development :: Libraries :: Python Modules
Requires-Python: >=3.12
Requires-Dist: exonware-xwnode
Requires-Dist: exonware-xwsystem
Provides-Extra: dev
Requires-Dist: black>=23.0.0; extra == 'dev'
Requires-Dist: isort>=5.12.0; extra == 'dev'
Requires-Dist: mypy>=1.0.0; extra == 'dev'
Requires-Dist: pytest-asyncio>=0.21.0; extra == 'dev'
Requires-Dist: pytest-cov>=4.0.0; extra == 'dev'
Requires-Dist: pytest>=7.0.0; extra == 'dev'
Provides-Extra: full
Requires-Dist: exonware-xwnode[full]; extra == 'full'
Requires-Dist: exonware-xwsystem[full]; extra == 'full'
Requires-Dist: json5>=0.9.0; extra == 'full'
Requires-Dist: pyyaml>=6.0.0; extra == 'full'
Requires-Dist: toml>=0.10.0; extra == 'full'
Provides-Extra: lazy
Requires-Dist: exonware-xwnode[lazy]; extra == 'lazy'
Requires-Dist: exonware-xwsystem[lazy]; extra == 'lazy'
